pydgn/__init__.py
pydgn/build_dataset.py
pydgn/launch_experiment.py
pydgn/static.py
pydgn/data/__init__.py
pydgn/data/dataset.py
pydgn/data/provider.py
pydgn/data/sampler.py
pydgn/data/splitter.py
pydgn/data/transform.py
pydgn/data/util.py
pydgn/evaluation/__init__.py
pydgn/evaluation/config.py
pydgn/evaluation/evaluator.py
pydgn/evaluation/grid.py
pydgn/evaluation/random_search.py
pydgn/evaluation/util.py
pydgn/experiment/__init__.py
pydgn/experiment/experiment.py
pydgn/experiment/semi_supervised_task.py
pydgn/experiment/supervised_task.py
pydgn/experiment/util.py
pydgn/log/__init__.py
pydgn/log/logger.py
pydgn/model/__init__.py
pydgn/model/interface.py
pydgn/model/dgn/__init__.py
pydgn/model/dgn/toy_dgn.py
pydgn/model/dgn/toy_mlp.py
pydgn/model/readout/__init__.py
pydgn/model/readout/graph_readout.py
pydgn/model/readout/link_readout.py
pydgn/model/readout/node_readout.py
pydgn/training/__init__.py
pydgn/training/engine.py
pydgn/training/profiler.py
pydgn/training/util.py
pydgn/training/callback/__init__.py
pydgn/training/callback/early_stopping.py
pydgn/training/callback/engine_callback.py
pydgn/training/callback/gradient_clipping.py
pydgn/training/callback/metric.py
pydgn/training/callback/optimizer.py
pydgn/training/callback/plotter.py
pydgn/training/callback/scheduler.py
pydgn/training/event/__init__.py
pydgn/training/event/dispatcher.py
pydgn/training/event/handler.py
pydgn/training/event/state.py
pydgn-1.6.0.dist-info/LICENSE
pydgn-1.6.0.dist-info/METADATA
pydgn-1.6.0.dist-info/WHEEL
pydgn-1.6.0.dist-info/entry_points.txt
pydgn-1.6.0.dist-info/top_level.txt
pydgn-1.6.0.dist-info/RECORD
