Metadata-Version: 2.1
Name: pydgn
Version: 1.6.0
Summary: A Python Package for Deep Graph Networks
Author-email: Federico Errica <f.errica@protonmail.com>
Project-URL: Homepage, https://pydgn.readthedocs.io/en/latest/
Keywords: deep-graph-networks,evaluation-framework,deep-learning-for-graphs
Classifier: Programming Language :: Python :: 3
Classifier: License :: OSI Approved :: BSD License
Classifier: Operating System :: OS Independent
Requires-Python: >=3.8
License-File: LICENSE
Requires-Dist: PyYAML >=5.4
Requires-Dist: tqdm >=4.66.1
Requires-Dist: Requests >=2.31.0
Requires-Dist: scikit-learn >=1.3.0
Requires-Dist: tensorboard >=2.11.0
Requires-Dist: tqdm >=4.47.0
Requires-Dist: ogb >=1.2.0
Requires-Dist: ray >=2.6.0
Requires-Dist: torch >=2.0.0
Requires-Dist: torch-geometric >=2.3.0
